xlinjietool/__init__.py
xlinjietool/converter.py
xlinjietool-0.0.1.dist-info/LICENSE
xlinjietool-0.0.1.dist-info/METADATA
xlinjietool-0.0.1.dist-info/WHEEL
xlinjietool-0.0.1.dist-info/entry_points.txt
xlinjietool-0.0.1.dist-info/top_level.txt
xlinjietool-0.0.1.dist-info/RECORD
