Metadata-Version: 2.1
Name: xlinjietool
Version: 0.0.1
Summary: 工具库
Home-page: https://github.com/Xlj997/xlinjietool
Author: Linjie Xing
Author-email: jin.951107@gmail.com
License: UNKNOWN
Platform: UNKNOWN
Classifier: Programming Language :: Python :: 3
Classifier: License :: OSI Approved :: MIT License
Classifier: Operating System :: OS Independent
License-File: LICENSE
